sqltranslate/DatabaseInfo.py
sqltranslate/__init__.py
sqltranslate/__main__.py
sqltranslate/cli.py
sqltranslate/sqltranslate.py
sqltranslate-0.1.4.dist-info/AUTHORS.rst
sqltranslate-0.1.4.dist-info/LICENSE.txt
sqltranslate-0.1.4.dist-info/METADATA
sqltranslate-0.1.4.dist-info/WHEEL
sqltranslate-0.1.4.dist-info/entry_points.txt
sqltranslate-0.1.4.dist-info/top_level.txt
sqltranslate-0.1.4.dist-info/RECORD
